{
  "name": "Medusa",
  "hero": {
    "name": "Medusa",
    "isRanged": true,
    "hp": 16,
    "move": 3,
    "specialAbility": "At the start of your turn, you may deal 1 damage to an opposing fighter in Medusa's zone."
  },
  "cards": [
    {
      "title": "Dash",
      "type": "versatile",
      "characterName": "ANY",
      "value": 3,
      "boost": 1,
      "basicText": null,
      "immediateText": null,
      "duringText": null,
      "afterText": "Move your fighter up to 3 spaces.",
      "imageUrl": null,
      "quantity": 3
    },
    {
      "title": "Gaze of Stone",
      "type": "attack",
      "characterName": "MEDUSA",
      "value": 2,
      "boost": 4,
      "basicText": null,
      "immediateText": null,
      "duringText": null,
      "afterText": "If you won the combat, deal 8 damage to the opposing fighter.",
      "imageUrl": null,
      "quantity": 3
    },
    {
      "title": "A Momentary Glance",
      "type": "scheme",
      "characterName": "MEDUSA",
      "value": null,
      "boost": 4,
      "basicText": "Deal 2 damage to any one fighter in Medusa's zone.",
      "immediateText": null,
      "duringText": null,
      "afterText": null,
      "imageUrl": null,
      "quantity": 2
    },
    {
      "title": "Hiss and Slither",
      "type": "defence",
      "characterName": "MEDUSA",
      "value": 4,
      "boost": 3,
      "basicText": null,
      "immediateText": null,
      "duringText": null,
      "afterText": "Your opponent discards 1 card.",
      "imageUrl": null,
      "quantity": 3
    },
    {
      "title": "The Hounds of Mighty Zeus",
      "type": "versatile",
      "characterName": "HARPY",
      "value": 4,
      "boost": 3,
      "basicText": null,
      "immediateText": null,
      "duringText": null,
      "afterText": "Move each Harpy up to 3 spaces.",
      "imageUrl": null,
      "quantity": 2
    },
    {
      "title": "Clutching Claws",
      "type": "versatile",
      "characterName": "HARPY",
      "value": 3,
      "boost": 2,
      "basicText": null,
      "immediateText": null,
      "duringText": null,
      "afterText": "Your opponent discards 1 card.",
      "imageUrl": null,
      "quantity": 3
    },
    {
      "title": "Winged Frenzy",
      "type": "scheme",
      "characterName": "ANY",
      "value": null,
      "boost": 2,
      "basicText": "Move each of your fighters up to 3 spaces. You may move them through spaces containing opposing fighters. Then, return a defeated Harpy (if any) to any space in Medusa's zone.",
      "immediateText": null,
      "duringText": null,
      "afterText": null,
      "imageUrl": null,
      "quantity": 2
    },
    {
      "title": "Second Shot",
      "type": "attack",
      "characterName": "MEDUSA",
      "value": 3,
      "boost": 3,
      "basicText": null,
      "immediateText": null,
      "duringText": "You may BOOST this attack.",
      "afterText": null,
      "imageUrl": null,
      "quantity": 3
    },
    {
      "title": "Snipe",
      "type": "versatile",
      "characterName": "ANY",
      "value": 3,
      "boost": 1,
      "basicText": null,
      "immediateText": null,
      "duringText": null,
      "afterText": "Draw 1 card.",
      "imageUrl": null,
      "quantity": 3
    },
    {
      "title": "Feint",
      "type": "versatile",
      "characterName": "ANY",
      "value": 2,
      "boost": 2,
      "basicText": null,
      "immediateText": "Cancel all effects on your opponent's card.",
      "duringText": null,
      "afterText": null,
      "imageUrl": null,
      "quantity": 3
    },
    {
      "title": "Regroup",
      "type": "versatile",
      "characterName": "ANY",
      "value": 1,
      "boost": 2,
      "basicText": null,
      "immediateText": null,
      "duringText": null,
      "afterText": "Draw 1 card. If you won the combat, draw 2 cards instead.",
      "imageUrl": null,
      "quantity": 3
    }
  ]
}